bioxelnodes/__init__.py
bioxelnodes/assets/Nodes/BioxelNodes_4.0.blend
bioxelnodes/assets/Nodes/BioxelNodes_4.1.blend
bioxelnodes/auto_load.py
bioxelnodes/customnodes/__init__.py
bioxelnodes/customnodes/menus.py
bioxelnodes/customnodes/nodes.py
bioxelnodes/externalpackage/__init__.py
bioxelnodes/externalpackage/package.py
bioxelnodes/externalpackage/preferences.py
bioxelnodes/io.py
bioxelnodes/io_points.py
bioxelnodes/menus.py
bioxelnodes/misc.py
bioxelnodes/nodes.py
bioxelnodes/operators.py
bioxelnodes/preferences.py
bioxelnodes/props.py
bioxelnodes/requirements.txt
bioxelnodes/utils.py
bioxelnodes-0.2.0.dist-info/LICENSE
bioxelnodes-0.2.0.dist-info/METADATA
bioxelnodes-0.2.0.dist-info/WHEEL
bioxelnodes-0.2.0.dist-info/RECORD
