Metadata-Version: 2.1
Name: bioxelnodes
Version: 0.2.0
Summary: 
License: MIT
Author: Ma Nan
Author-email: icrdr2010@outlook.com
Requires-Python: >=3.10.0,<3.11.0
Classifier: License :: OSI Approved :: MIT License
Classifier: Programming Language :: Python :: 3
Classifier: Programming Language :: Python :: 3.10
Requires-Dist: bpy (>=4.0,<5.0)
Requires-Dist: simpleitk (>=2.3.1,<3.0.0)
